pystatik/__init__.py
pystatik-0.2.2.dist-info/LICENSE
pystatik-0.2.2.dist-info/METADATA
pystatik-0.2.2.dist-info/WHEEL
pystatik-0.2.2.dist-info/top_level.txt
pystatik-0.2.2.dist-info/RECORD
