Metadata-Version: 2.1
Name: pystatik
Version: 0.2.2
Summary: Türkçe fonksiyonlarla sade istatistik kütüphanesi
Home-page: https://github.com/pozstudiox/pystatic
Author: PozStudio
Author-email: pozstudiosh@gmail.com
Keywords: istatistik python türkçe egitim medyan ortalama sapma mod
Classifier: Programming Language :: Python :: 3
Classifier: Operating System :: OS Independent
Classifier: Intended Audience :: Education
Classifier: Topic :: Scientific/Engineering :: Mathematics
Requires-Python: >=3.6
License-File: LICENSE
